Metadata-Version: 2.4
Name: mcp-toolbox-fastmcp
Version: 0.0.1.dev0
Summary: Maintenance of a set of tools to enhance LLM through MCP protocols.
Project-URL: Homepage, https://github.com/fastmcp-me/mcp-toolbox#readme
Project-URL: Repository, https://github.com/fastmcp-me/mcp-toolbox.git
Project-URL: Issues, https://github.com/fastmcp-me/mcp-toolbox/issues
Author-email: ai-zerolab <jizhongsheng957@gmail.com>
License-File: LICENSE
Keywords: LLM,MCP,Model Context Protocol
Classifier: Intended Audience :: Developers
Classifier: Programming Language :: Python
Classifier: Programming Language :: Python :: 3
Classifier: Programming Language :: Python :: 3.10
Classifier: Programming Language :: Python :: 3.11
Classifier: Programming Language :: Python :: 3.12
Classifier: Programming Language :: Python :: 3.13
Classifier: Topic :: Software Development :: Libraries :: Python Modules
Requires-Python: >=3.10
Requires-Dist: anyio>=4.8.0
Requires-Dist: duckduckgo-search>=7.5.2
Requires-Dist: httpx>=0.28.1
Requires-Dist: loguru>=0.7.3
Requires-Dist: markitdown[all]~=0.1.0a1
Requires-Dist: mcp[cli]>=1.3.0
Requires-Dist: numpy>=2.1.3
Requires-Dist: pillow>=11.1.0
Requires-Dist: pydantic-settings[toml]>=2.8.0
Requires-Dist: pydantic>=2.10.6
Requires-Dist: tavily-python>=0.5.1
Requires-Dist: typer>=0.15.2
Provides-Extra: all
Requires-Dist: mcp-toolbox[audio,memory]; extra == 'all'
Provides-Extra: audio
Requires-Dist: openai-whisper>=20240930; (python_version <= '3.12') and extra == 'audio'
Provides-Extra: memory
Requires-Dist: fastembed>=0.6.0; extra == 'memory'
Requires-Dist: portalocker>=3.1.1; extra == 'memory'
